ivaoauroraconnect/__init__.py
ivaoauroraconnect/commands.py
ivaoauroraconnect-0.5.dist-info/METADATA
ivaoauroraconnect-0.5.dist-info/WHEEL
ivaoauroraconnect-0.5.dist-info/top_level.txt
ivaoauroraconnect-0.5.dist-info/RECORD
