Metadata-Version: 2.4
Name: ivaoauroraconnect
Version: 0.5
Summary: This is library for work with IVAO Aurora
Home-page: https://github.com/LevLvovich1/ivaoauroraconnect
Author: LevLvovich1
Author-email: levlogvinov@gmail.com
Project-URL: GitHub, https://github.com/LevLvovich1/ivaoauroraconnect
Keywords: ivao
Classifier: Programming Language :: Python :: 3.13
Classifier: License :: OSI Approved :: MIT License
Classifier: Operating System :: OS Independent
Requires-Python: >=3.13
Dynamic: author
Dynamic: author-email
Dynamic: classifier
Dynamic: description
Dynamic: description-content-type
Dynamic: home-page
Dynamic: keywords
Dynamic: project-url
Dynamic: requires-python
Dynamic: summary
